vim_kernel/__init__.py
vim_kernel/__main__.py
vim_kernel/autoload/vimkernel.vim
vim_kernel/install.py
vim_kernel/kernel.json
vim_kernel/kernel.py
vim_kernel/kernel.vim
vim_kernel/logo-32x32.png
vim_kernel/logo-64x64.png
vim_kernel-0.0.4.dist-info/WHEEL
vim_kernel-0.0.4.dist-info/METADATA
vim_kernel-0.0.4.dist-info/RECORD
