Metadata-Version: 2.1
Name: vim-kernel
Version: 0.0.4
Summary: A Jupyter kernel for Vim script
Author: mattn
Author-email: mattn.jp@gmail.com
Requires-Python: >=3.6,<4.0
Classifier: Programming Language :: Python :: 3
Classifier: Programming Language :: Python :: 3.6
Classifier: Programming Language :: Python :: 3.7
Classifier: Programming Language :: Python :: 3.8
Requires-Dist: notebook (>=6.0.3,<7.0.0)
